whiteboard/__init__.py
whiteboard/app.py
whiteboard/cli.py
whiteboard/static/edit.js
whiteboard/static/style.css
whiteboard/templates/base.html
whiteboard/templates/edit.html
whiteboard/templates/list.html
whiteboard-0.1.1.dist-info/DESCRIPTION.rst
whiteboard-0.1.1.dist-info/METADATA
whiteboard-0.1.1.dist-info/RECORD
whiteboard-0.1.1.dist-info/WHEEL
whiteboard-0.1.1.dist-info/entry_points.txt
whiteboard-0.1.1.dist-info/metadata.json
whiteboard-0.1.1.dist-info/top_level.txt
