Metadata-Version: 1.1
Name: whiteboard
Version: 0.1.1
Summary: Take math notes in your browser
Home-page: https://github.com/nickfrostatx/whiteboard
Author: Nick Frost
Author-email: nickfrostatx@gmail.com
License: MIT
Platform: UNKNOWN
Classifier: Development Status :: 3 - Alpha
Classifier: Framework :: Flask
Classifier: License :: OSI Approved :: MIT License
Classifier: Programming Language :: Python :: 2
Classifier: Programming Language :: Python :: 3
Classifier: Topic :: Text Editors
